gossip_flask/__init__.py
gossip_flask/db.py
gossip_flask/server.py
gossip_flask/utils.py
gossip_flask-0.1.0.dist-info/WHEEL
gossip_flask-0.1.0.dist-info/entry_points.txt
gossip_flask-0.1.0.dist-info/METADATA
gossip_flask-0.1.0.dist-info/RECORD
