Metadata-Version: 2.3
Name: gossip-flask
Version: 0.1.0
Summary: Add your description here
Author: David Cheeseman
Author-email: David Cheeseman <5287736+nuvious@users.noreply.github.com>
Requires-Dist: flasgger>=0.9.7.1
Requires-Dist: flask>=3.1.2
Requires-Dist: requests>=2.32.5
Requires-Dist: scipy>=1.16.2
Requires-Dist: semver>=3.0.4
Requires-Dist: sqlalchemy>=2.0.43
Requires-Python: >=3.11
